jdauto/__init__.py
jdauto/_version.py
jdauto/jdauto.py
jdauto-0.0.8.dist-info/LICENSE
jdauto-0.0.8.dist-info/METADATA
jdauto-0.0.8.dist-info/WHEEL
jdauto-0.0.8.dist-info/entry_points.txt
jdauto-0.0.8.dist-info/top_level.txt
jdauto-0.0.8.dist-info/zip-safe
jdauto-0.0.8.dist-info/RECORD
