Metadata-Version: 2.1
Name: jdauto
Version: 0.0.8
Summary: Autocollect service for Jackdaw
Home-page: https://github.com/skelsec/jdauto
Author: Tamas Jos
Author-email: info@skelsec.com
License: UNKNOWN
Platform: UNKNOWN
Classifier: Programming Language :: Python :: 3.6
Classifier: License :: OSI Approved :: MIT License
Classifier: Operating System :: OS Independent
Requires-Python: >=3.6
Requires-Dist: aiosmb (>=0.2.20)
Requires-Dist: jackdaw (>=0.2.21)
Requires-Dist: msldap (>=0.3.9)
Requires-Dist: multiplexor (>=0.0.12)
Requires-Dist: pypykatz (>=0.3.11)
